minimal_pairs/__init__.py
minimal_pairs/arpabet.py
minimal_pairs/minimal_pairs.py
tests/__init__.py
tests/test_arpabet.py
tests/test_minimal_pairs.py
minimal_pairs-0.1.0.dist-info/LICENSE
minimal_pairs-0.1.0.dist-info/METADATA
minimal_pairs-0.1.0.dist-info/WHEEL
minimal_pairs-0.1.0.dist-info/top_level.txt
minimal_pairs-0.1.0.dist-info/RECORD
